BloxPy/Badges.py
BloxPy/Groups.py
BloxPy/Search.py
BloxPy/Users.py
BloxPy/__init__.py
_exceptions/RobloxExceptions.py
_exceptions/__init__.py
BloxPy-0.1.15.dist-info/LICENSE
BloxPy-0.1.15.dist-info/METADATA
BloxPy-0.1.15.dist-info/WHEEL
BloxPy-0.1.15.dist-info/top_level.txt
BloxPy-0.1.15.dist-info/RECORD
